auth0_jwt_validator/__init__.py
auth0_jwt_validator/http_bearer.py
auth0_jwt_validator/jwt_verifier.py
auth0_jwt_validator-1.2.dist-info/WHEEL
auth0_jwt_validator-1.2.dist-info/METADATA
auth0_jwt_validator-1.2.dist-info/RECORD
