Metadata-Version: 2.1
Name: auth0-jwt-validator
Version: 1.2
Summary: Python Auth0 JWT Validator
Author-email: Danilo Britto <dbritto.dev@gmail.com>
Requires-Python: >=3.8
Classifier: Intended Audience :: Information Technology
Classifier: Intended Audience :: System Administrators
Classifier: Operating System :: OS Independent
Classifier: Programming Language :: Python :: 3
Classifier: Programming Language :: Python
Classifier: Topic :: Internet
Classifier: Topic :: Software Development :: Libraries :: Python Modules
Classifier: Topic :: Software Development :: Libraries
Classifier: Topic :: Software Development
Classifier: Typing :: Typed
Classifier: Intended Audience :: Developers
Classifier: License :: OSI Approved :: MIT License
Classifier: Programming Language :: Python :: 3 :: Only
Classifier: Programming Language :: Python :: 3.8
Classifier: Programming Language :: Python :: 3.9
Classifier: Programming Language :: Python :: 3.10
Classifier: Topic :: Internet :: WWW/HTTP
Classifier: Topic :: Security
Requires-Dist: Authlib
Requires-Dist: pytest >=7 ; extra == "ci"
Requires-Dist: pytest-cov ; extra == "ci"
Requires-Dist: pytest-mock ; extra == "ci"
Requires-Dist: faker ; extra == "ci"
Requires-Dist: isort ; extra == "ci"
Requires-Dist: black ; extra == "ci"
Requires-Dist: flake8 ; extra == "ci"
Requires-Dist: bandit ; extra == "ci"
Requires-Dist: safety ; extra == "ci"
Requires-Dist: isort ; extra == "dev"
Requires-Dist: black ; extra == "dev"
Requires-Dist: flake8 ; extra == "dev"
Requires-Dist: bandit ; extra == "dev"
Requires-Dist: safety ; extra == "dev"
Requires-Dist: pdoc ; extra == "doc"
Requires-Dist: pytest >=7 ; extra == "test"
Requires-Dist: pytest-cov ; extra == "test"
Requires-Dist: pytest-mock ; extra == "test"
Requires-Dist: faker ; extra == "test"
Project-URL: Documentation, https://github.com/immersa-co/python-jwt-auth0-validator
Project-URL: Source, https://github.com/immersa-co/python-jwt-auth0-validator
Provides-Extra: ci
Provides-Extra: dev
Provides-Extra: doc
Provides-Extra: test
